tensorpowerflow/__init__.py
tensorpowerflow/grid.py
tensorpowerflow/numbarize.py
tensorpowerflow/utils.py
tensorpowerflow/data/Lines_2.csv
tensorpowerflow/data/Lines_34.csv
tensorpowerflow/data/Nodes_2.csv
tensorpowerflow/data/Nodes_34.csv
tensorpowerflow/gpu_tensor/__init__.py
tensorpowerflow/gpu_tensor/gpu_interface.py
tensorpowerflow/pyMKL/MKLutils.py
tensorpowerflow/pyMKL/README.txt
tensorpowerflow/pyMKL/__init__.py
tensorpowerflow/pyMKL/loadMKL.py
tensorpowerflow/pyMKL/pardisoInterface.py
tensorpowerflow/pyMKL/pardisoSolver.py
tensorpowerflow/pyMKL/Tests/trial_MKLUtils.py
tensorpowerflow/pyMKL/Tests/trial_Pardiso.py
tensorpowerflow/tests/__init__.py
tensorpowerflow/tests/test_powerflows.py
tensorpowerflow/tests/test_powerflows_pardiso_gpu.py
tensorpowerflow/tests/test_tensor_power_flow.py
tensorpowerflow-0.0.7.dist-info/LICENSE
tensorpowerflow-0.0.7.dist-info/METADATA
tensorpowerflow-0.0.7.dist-info/WHEEL
tensorpowerflow-0.0.7.dist-info/top_level.txt
tensorpowerflow-0.0.7.dist-info/RECORD
