Metadata-Version: 2.1
Name: tensorpowerflow
Version: 0.0.7
Summary: Ultra fast power flow based in Laurent series expansion.
Author-email: Mauricio Salazar <e.m.salazar.duque@tue.nl>
License: MIT
Project-URL: repository, https://github.com/MauricioSalazare/tensorpowerflow
Keywords: power flow,power systems,time series loading
Classifier: Programming Language :: Python :: 3
Classifier: License :: OSI Approved :: MIT License
Classifier: Operating System :: OS Independent
Requires-Python: >=3.0
License-File: LICENSE
Requires-Dist: numpy
Requires-Dist: pandas
Requires-Dist: matplotlib
Requires-Dist: scipy
Requires-Dist: tqdm
Requires-Dist: numba >=0.53.0
Requires-Dist: networkx
Requires-Dist: seaborn
Requires-Dist: pandapower
Requires-Dist: psutil
Requires-Dist: mkl ; platform_system != "Darwin"
Provides-Extra: dev
Requires-Dist: build ; extra == 'dev'
Requires-Dist: twine ; extra == 'dev'
Requires-Dist: matplotlib ; extra == 'dev'
Requires-Dist: jupyterlab ; extra == 'dev'
Requires-Dist: tox ; extra == 'dev'
Provides-Extra: doc
Requires-Dist: sphinx ; extra == 'doc'
Provides-Extra: test
Requires-Dist: pytest ; extra == 'test'
